smsframework/Gateway.py
smsframework/IProvider.py
smsframework/__init__.py
smsframework/exc.py
smsframework/data/IncomingMessage.py
smsframework/data/MessageStatus.py
smsframework/data/OutgoingMessage.py
smsframework/data/OutgoingMessageOptions.py
smsframework/data/__init__.py
smsframework/lib/__init__.py
smsframework/lib/events.py
smsframework/providers/__init__.py
smsframework/providers/log.py
smsframework/providers/loopback.py
smsframework/providers/null.py
smsframework/providers/forward/__init__.py
smsframework/providers/forward/jsonex.py
smsframework/providers/forward/provider.py
smsframework/providers/forward/receiver_client.py
smsframework/providers/forward/receiver_server.py
smsframework-0.0.9.post3.dist-info/LICENSE
smsframework-0.0.9.post3.dist-info/METADATA
smsframework-0.0.9.post3.dist-info/WHEEL
smsframework-0.0.9.post3.dist-info/top_level.txt
smsframework-0.0.9.post3.dist-info/RECORD
