Metadata-Version: 2.1
Name: smsframework
Version: 0.0.9.post3
Summary: Bi-directional SMS gateway with pluggable providers 
Home-page: https://github.com/kolypto/py-smsframework
Author: Mark Vartanyan
Author-email: kolypto@gmail.com
License: BSD
Keywords: sms,message,notification,receive,send
Platform: any
Classifier: Development Status :: 5 - Production/Stable
Classifier: Intended Audience :: Developers
Classifier: Natural Language :: English
Classifier: Operating System :: OS Independent
Classifier: Programming Language :: Python :: 2
Classifier: Programming Language :: Python :: 3
Classifier: Topic :: Software Development :: Libraries :: Python Modules
Provides-Extra: async
Requires-Dist: asynctools (>=0.1.3) ; extra == 'async'
Provides-Extra: clickatell
Requires-Dist: smsframework-clickatell (>=0.0.3) ; extra == 'clickatell'
Provides-Extra: receiver
Requires-Dist: flask (>=0.10) ; extra == 'receiver'
Provides-Extra: vianett
Requires-Dist: smsframework-vianett (>=0.0.2) ; extra == 'vianett'
